torch_runner/__init__.py
torch_runner/config.py
torch_runner/train_module.py
torch_runner/utils.py
torch_runner-0.1.0.dist-info/LICENSE
torch_runner-0.1.0.dist-info/METADATA
torch_runner-0.1.0.dist-info/WHEEL
torch_runner-0.1.0.dist-info/top_level.txt
torch_runner-0.1.0.dist-info/RECORD
